nornir_napalm/__init__.py
nornir_napalm/plugins/__init__.py
nornir_napalm/plugins/connections/__init__.py
nornir_napalm/plugins/tasks/__init__.py
nornir_napalm/plugins/tasks/napalm_cli.py
nornir_napalm/plugins/tasks/napalm_configure.py
nornir_napalm/plugins/tasks/napalm_get.py
nornir_napalm/plugins/tasks/napalm_ping.py
nornir_napalm/plugins/tasks/napalm_validate.py
nornir_napalm-0.2.0.dist-info/entry_points.txt
nornir_napalm-0.2.0.dist-info/LICENSE
nornir_napalm-0.2.0.dist-info/WHEEL
nornir_napalm-0.2.0.dist-info/METADATA
nornir_napalm-0.2.0.dist-info/RECORD
