Metadata-Version: 2.1
Name: nornir-napalm
Version: 0.2.0
Summary: NAPALM's plugins for nornir
License: Apache-2.0
Author: David Barroso
Author-email: dbarrosop@dravetech.com
Requires-Python: >=3.7,<4.0
Classifier: License :: OSI Approved :: Apache Software License
Classifier: Programming Language :: Python :: 3
Classifier: Programming Language :: Python :: 3.10
Classifier: Programming Language :: Python :: 3.7
Classifier: Programming Language :: Python :: 3.8
Classifier: Programming Language :: Python :: 3.9
Requires-Dist: napalm (>=3,<4)
Requires-Dist: nornir (>=3,<4)
